fastlid/__init__.py
fastlid/__main__.py
fastlid/fastlid.py
fastlid/supported_langs.py
fastlid-0.1.12.dist-info/METADATA
fastlid-0.1.12.dist-info/WHEEL
fastlid-0.1.12.dist-info/RECORD
