Metadata-Version: 2.1
Name: fastlid
Version: 0.1.12
Summary: Detect languages via a fasttext model
Home-page: https://github.com/ffreemt/fast-langid
License: MIT
Author: freemt
Requires-Python: >=3.8,<3.10
Classifier: License :: OSI Approved :: MIT License
Classifier: Programming Language :: Python :: 3
Classifier: Programming Language :: Python :: 3.8
Classifier: Programming Language :: Python :: 3.9
Requires-Dist: fasttext-wheel (>=0.9.2,<0.10.0)
Requires-Dist: logzero (>=1.7.0,<2.0.0)
Requires-Dist: numpy (>=1.20.3,<2.0.0)
Project-URL: Repository, https://github.com/ffreemt/fast-langid
